    {"BirthDate":"1961-10-26",
     "DirectoryRelease":true,
     "Email":"james@uw.edu",
     "EmployeeID":"123456789",
     "FirstName":"JAMES AVERAGE",
     "Gender":"M",
     "LastEnrolled":null,
     "LastName":"TEACHER",
     "Pronouns": "he/him/his",
     "LocalAddress":{"City":"SEATTLE",
        "Country":"United States",
        "Line1":"4634 26th Ave NE",
        "Line2":"APT 102",
        "PostalCode":"",
        "State":"WA",
        "Zip":"98105"},
     "LocalPhone":"2063333333",
     "PermanentAddress":{
        "City":"Bellevue",
        "Country":"",
        "Line1":"1645 140th Ave NE",
        "Line2":"APT 980",
        "PostalCode":"",
        "State":"WA",
        "Zip":"98005-1234"},
     "PermanentPhone":"2065555555",
     "RegID":"260A0DEC95CB11D78BAA000629C31437",
     "Resident":"1",
     "ResidencyDescription": "RESIDENT",
     "StudentName":"JAMES AVERAGE TEACHER",
     "StudentNumber":"1033334",
     "StudentSystemKey":"000083856",
     "TestScore":{"Href":"\/student\/v5\/testscore\/260A0DEC95CB11D78BAA000629C31437.json",
                  "RegID":"260A0DEC95CB11D78BAA000629C31437"},
     "UWNetID":"james",
     "Veteran":{"Code":"0",
                "Description": "NOT A VET"
               },
     "VisaType":""}
