{ "AddAccessCode" : "",
  "Auditor" : false,
  "Credits" : "5.0",
  "DropAccessCode" : "",
  "DuplicateCode" : "1",
  "FacultySequenceNumber" : "",
  "FeeBaseType" : "",
  "Grade" : "X",
  "GradeDate" : "",
  "GradeDocumentID" : "000000000",
  "HonorsCourse" : false,
  "IsActive" : true,
  "Person" : { "Href" : "\/student\/v4\/person\/9136CCB8F66711D5BE060004AC494FFE.json",
      "Name" : "Student, Seattle Average",
      "RegID" : "9136CCB8F66711D5BE060004AC494FFE"
    },
  "RepeatCourse" : false,
  "RequestDate" : "",
  "RequestStatus" : "",
  "Section" : { "CourseNumber" : "100",
      "CurriculumAbbreviation" : "TRAIN",
      "Href" : "\/student\/v4\/course\/2012,summer,TRAIN,100\/A.json",
      "Quarter" : "summer",
      "SectionID" : "A",
      "Year" : "2012"
    },
  "VariableCredit" : false,
  "WritingCourse" : false
}
